kelvin/krn/__init__.py
kelvin/krn/krn.py
kelvin/krn/py.typed
kelvin/krn/version.py
kelvin_krn-0.1.1.dist-info/METADATA
kelvin_krn-0.1.1.dist-info/WHEEL
kelvin_krn-0.1.1.dist-info/top_level.txt
kelvin_krn-0.1.1.dist-info/RECORD
