Metadata-Version: 2.4
Name: kelvin-krn
Version: 0.1.1
Summary: Kelvin Resource Name (KRN) library
Author-email: Kelvin Inc <engineering@kelvininc.com>
Classifier: Operating System :: OS Independent
Classifier: Programming Language :: Python :: 3
Requires-Python: <3.14,>=3.9
Requires-Dist: pydantic==2.11.*
Requires-Dist: typing-extensions==4.*
